stator/core.cpython-38-x86_64-linux-gnu.so
stator/__init__.py
stator-0.0.2.dist-info/WHEEL
stator-0.0.2.dist-info/METADATA
stator-0.0.2.dist-info/top_level.txt
stator-0.0.2.dist-info/RECORD
