Metadata-Version: 2.1
Name: stator
Version: 0.0.2
Summary: The python stator interface.
Home-page: https://github.com/toastedcrumpets/stator
Author: Marcus Bannerman
Author-email: m.bannerman@gmail.com
License: UNKNOWN
Platform: UNKNOWN
Provides-Extra: test
Requires-Dist: pytest ; extra == 'test'
